mfe_saw/__init__.py
mfe_saw/base.py
mfe_saw/cli.py
mfe_saw/datasource.py
mfe_saw/esm.py
mfe_saw/exceptions.py
mfe_saw/params.py
mfe_saw/utils.py
mfe_saw/version.py
mfe_saw-0.0.8.dist-info/DESCRIPTION.rst
mfe_saw-0.0.8.dist-info/METADATA
mfe_saw-0.0.8.dist-info/RECORD
mfe_saw-0.0.8.dist-info/WHEEL
mfe_saw-0.0.8.dist-info/entry_points.txt
mfe_saw-0.0.8.dist-info/metadata.json
mfe_saw-0.0.8.dist-info/top_level.txt
